{
    "success": {
        "v": 2,
        "license": "CC-BY 4.0",
        "data": [
            {
                "col_id": 1497,
                "col_name": "Turner Valley",
                "col_group": "Canadian Cordillera III",
                "col_group_id": 40,
                "group_col_id": "88.00",
                "lat": "50.01100",
                "lng": "-114.26500",
                "col_area": "5434.6",
                "project_id": 1,
                "col_type": "column",
                "refs": [
                    10
                ]
            },
            {
                "col_id": 1642,
                "col_name": "Turner Valley",
                "col_group": "Prairie Provinces and British Columbia",
                "col_group_id": 45,
                "group_col_id": "57.00",
                "lat": "50.45900",
                "lng": "-114.27600",
                "col_area": "7393.5",
                "project_id": 1,
                "col_type": "column",
                "refs": [
                    12
                ]
            }
        ],
        "refs": {
            "10": "H. Gabrielse and A.J. Brookfield. Correlation chart for the Canadian Cordiellera. 1988. ",
            "12": "Stott, D.F. Geotectonic correlation charts. in Sedimentary Cover of the North American craton: Canada. GSC Geology of Canada No. 5. 1991. "
        }
    }
}